hdfc_cc_parser_rs-0.0.7.dist-info/METADATA
hdfc_cc_parser_rs-0.0.7.dist-info/WHEEL
hdfc_cc_parser/__init__.py
hdfc_cc_parser/hdfc_cc_parser.cpython-310-darwin.so
hdfc_cc_parser_rs-0.0.7.dist-info/RECORD
