Metadata-Version: 2.4
Name: hdfc-cc-parser-rs
Version: 0.0.7
Keywords: HDFC,credit card,bill
Author: Joe Paul <joeirimpan@gmail.com>
Author-email: Joe Paul <joeirimpan@gmail.com>
License: MIT
Project-URL: Source Code, https://github.com/joeirimpan/hdfc-cc-parser-rs
